{"vaccination": ["cubeer burr", "bajra", "pinjrapole", "dinapore", "bottle-tree", "babagooree", "nujeeb", "honore", "cambay", "brazil-wood"], "vaishnava": [], "vakeel": [], "varella": ["swamy-pagoda", "combaconum", "canteroy", "rut", "joss", "typhoon", "prow", "malacca", "grab", "winter"], "vedas": [], "veddas": [], "vellard": ["dumdum", "jungeera", "bund", "bandaree", "foras lands", "congee", "governor's straits", "cobily mash", "cantonment", "caravan"], "vellore": ["chillumbrum", "poonamalee", "tanjore", "combaconum", "babool", "tuticorin", "gingi", "cuddalore", "tinnevelly", "salempoory"], "vendu-master": ["caryota", "mocuddum", "bankshall", "pundit", "magadoxo", "melinde", "mussaulchee", "collector", "pice", "bombay marine"], "venetian": [], "veranda": ["roc", "narrows", "sind\u0101b\u016br", "bankshall", "malacca", "cuttack", "gallevat", "sweet potato", "carraway", "trincomalee"], "verdure": [], "vettyver": [], "vidana": ["chuckrum", "dondera head", "dar\u00f3ga", "bhyacharra", "jompon", "zemindar", "toomongong", "khan", "bend\u00e1ra", "dooputty"], "vihara": ["cooch behar", "cootub", "nowbehar", "diul-sind", "camboja", "mutt", "ell'ora", "hokchew", "bisnagar", "lee"], "viss": ["frazala", "culsey", "tola", "tical", "candareen", "misree", "cash", "mergui", "bahar", "fan\u00e1m"], "vizier": ["nizam", "idalcan", "madremaluco", "toomongong", "raja", "khan", "sahib", "sophy", "nab\u00f3b", "destoor"]}